[
    {
        "Сторона A":7,
        "Сторона B":15,
        "Сторона C":10.869573067471679,
        "Угол":51,"Площадь":35.187031731777175
    },
    {
        "Сторона A":4,
        "Сторона B":6,
        "Сторона C":8.92726747606801,
        "Угол":109,
        "Площадь":9.800911279635804
    },
    {
        "Сторона A":4,
        "Сторона B":13,
        "Сторона C":14.61564186607506,
        "Угол":17,
        "Площадь":24.996334788868477
    },
    {
        "Сторона A":7,
        "Сторона B":6,
        "Сторона C":10.533656020867111,
        "Угол":71,
        "Площадь":19.97214771834187
    },
    {
        "Сторона A":12,
        "Сторона B":7,
        "Сторона C":6.937609779720182,
        "Угол":100,
        "Площадь":21.26735692660987
    }
]